LICENSE.txt
README.md
setup.py
sclib/__init__.py
sclib/asyncio.py
sclib/sync.py
sclib/util.py
soundcloud_lib.egg-info/PKG-INFO
soundcloud_lib.egg-info/SOURCES.txt
soundcloud_lib.egg-info/dependency_links.txt
soundcloud_lib.egg-info/requires.txt
soundcloud_lib.egg-info/top_level.txt