Metadata-Version: 2.1
Name: soundcloud-lib
Version: 0.6.1
Summary: Python Soundcloud API
Home-page: https://github.com/3jackdaws/soundcloud-lib
Author: Ian Murphy
Author-email: 3jackdaws@gmail.com
License: MIT
Platform: UNKNOWN
Requires-Python: >=3.6
License-File: LICENSE.txt
